onliner_parser/__init__.py
onliner_parser/input_manager.py
onliner_parser/models.py
onliner_parser/parser.py
onliner_parser/save_manager.py
onliner_parser/terminal_font_style.py
onliner_parser/managers/__init__.py
onliner_parser/managers/data_processing_manager.py
onliner_parser/managers/input_manager.py
onliner_parser/managers/load_manager.py
onliner_parser/managers/save_manager.py
onliner_parser/utils/__init__.py
onliner_parser/utils/data_transformation.py
onliner_parser/utils/decorators.py
onliner_parser/utils/font_settings.py
onliner_parser/utils/settings.py
onliner_parser-0.2.2.1.dist-info/METADATA
onliner_parser-0.2.2.1.dist-info/WHEEL
onliner_parser-0.2.2.1.dist-info/top_level.txt
onliner_parser-0.2.2.1.dist-info/RECORD
